pulpcore/__init__.py
pulpcore/client/__init__.py
pulpcore/client/pulp_python/__init__.py
pulpcore/client/pulp_python/api_client.py
pulpcore/client/pulp_python/api_response.py
pulpcore/client/pulp_python/configuration.py
pulpcore/client/pulp_python/exceptions.py
pulpcore/client/pulp_python/py.typed
pulpcore/client/pulp_python/rest.py
pulpcore/client/pulp_python/api/__init__.py
pulpcore/client/pulp_python/api/api_legacy_api.py
pulpcore/client/pulp_python/api/api_pypi_api.py
pulpcore/client/pulp_python/api/api_simple_api.py
pulpcore/client/pulp_python/api/content_packages_api.py
pulpcore/client/pulp_python/api/distributions_pypi_api.py
pulpcore/client/pulp_python/api/publications_pypi_api.py
pulpcore/client/pulp_python/api/pypi_metadata_api.py
pulpcore/client/pulp_python/api/remotes_python_api.py
pulpcore/client/pulp_python/api/repositories_python_api.py
pulpcore/client/pulp_python/api/repositories_python_versions_api.py
pulpcore/client/pulp_python/models/__init__.py
pulpcore/client/pulp_python/models/async_operation_response.py
pulpcore/client/pulp_python/models/content_summary_response.py
pulpcore/client/pulp_python/models/exclude_platforms_enum.py
pulpcore/client/pulp_python/models/my_permissions_response.py
pulpcore/client/pulp_python/models/nested_role.py
pulpcore/client/pulp_python/models/nested_role_response.py
pulpcore/client/pulp_python/models/object_roles_response.py
pulpcore/client/pulp_python/models/package_metadata_response.py
pulpcore/client/pulp_python/models/package_types_enum.py
pulpcore/client/pulp_python/models/package_upload_task_response.py
pulpcore/client/pulp_python/models/paginated_repository_version_response_list.py
pulpcore/client/pulp_python/models/paginatedpython_python_distribution_response_list.py
pulpcore/client/pulp_python/models/paginatedpython_python_package_content_response_list.py
pulpcore/client/pulp_python/models/paginatedpython_python_publication_response_list.py
crc_pulp_python_client-20251023.3.dist-info/METADATA
crc_pulp_python_client-20251023.3.dist-info/WHEEL
crc_pulp_python_client-20251023.3.dist-info/top_level.txt
crc_pulp_python_client-20251023.3.dist-info/RECORD
