Metadata-Version: 2.4
Name: crc-pulp_python-client
Version: 20251023.3
Summary: Pulp 3 API
Home-page: 
Author: Pulp Team
Author-email: pulp-list@redhat.com
License: GPLv2+
Keywords: pulp,pulpcore,client,Pulp 3 API
Requires-Dist: urllib3<3.0.0,>=1.25.3
Requires-Dist: python-dateutil<2.10.0,>=2.8.1
Requires-Dist: pydantic>=2
Requires-Dist: typing-extensions>=4.7.1
Dynamic: author
Dynamic: author-email
Dynamic: description
Dynamic: description-content-type
Dynamic: keywords
Dynamic: license
Dynamic: requires-dist
Dynamic: summary
